{
  "parent": "minecraft:recipes/root",
  "criteria": {
    "has_boost_asphalt": {
      "conditions": {
        "items": [
          {
            "items": [
              "citycraft:boost_asphalt"
            ]
          }
        ]
      },
      "trigger": "minecraft:inventory_changed"
    },
    "has_the_recipe": {
      "conditions": {
        "recipe": "citycraft:boost_asphalt_slab"
      },
      "trigger": "minecraft:recipe_unlocked"
    }
  },
  "requirements": [
    [
      "has_boost_asphalt",
      "has_the_recipe"
    ]
  ],
  "rewards": {
    "recipes": [
      "citycraft:boost_asphalt_slab"
    ]
  },
  "sends_telemetry_event": false
}